{"id":"sd_doh_joe-muggs-785-2130-haines-ave-rapid-city","name":"JOE MUGGS - 785","address":"2130 Haines AVE","city":"Rapid City","state":"SD","zip_code":null,"phone":null,"latitude":44.105882534551,"longitude":-103.221652431733,"source":"sd_doh","latest_score":100,"latest_inspection_date":"2026-01-26","average_score":100,"inspection_count":1,"has_critical_violations":false,"violation_categories":[],"inspections":[{"date":"2026-01-26","score":100,"grade":"A","inspection_type":"Routine","comments":"","violations":[]}],"score_history":[{"date":"2026-01-26","score":100}],"score_trend":null,"violation_history":[],"violation_trend":null}
