{"id":"sd_doh_hart-ranch-golf-course-23645-club-house-dr-rapid-city","name":"HART RANCH GOLF COURSE","address":"23645 Club House DR","city":"Rapid City","state":"SD","zip_code":null,"phone":null,"latitude":43.980452639611,"longitude":-103.239166516693,"source":"sd_doh","latest_score":100,"latest_inspection_date":"2026-05-14","average_score":100,"inspection_count":2,"has_critical_violations":false,"violation_categories":[],"score_history":[{"date":"2025-05-15","score":100},{"date":"2026-05-14","score":100}],"score_trend":"flat","violation_history":[{"date":"2025-05-15","count":0},{"date":"2026-05-14","count":0}],"violation_trend":"flat","inspections":[{"date":"2026-05-14","score":100,"grade":"A","inspection_type":"Routine","comments":"","violation_count":0,"violations":[]},{"date":"2025-05-15","score":100,"grade":"A","inspection_type":"Routine","comments":"","violation_count":0,"violations":[]}]}
