{"id":"sd_doh_the-salvation-army-1003-6th-sw-ave-aberdeen","name":"THE SALVATION ARMY","address":"1003 6th SW AVE","city":"Aberdeen","state":"SD","zip_code":null,"phone":null,"latitude":45.459376030494,"longitude":-98.502551198653,"source":"sd_doh","latest_score":97,"latest_inspection_date":"2026-02-12","average_score":98,"inspection_count":3,"has_critical_violations":true,"violation_categories":["cleanliness","contamination"],"inspections":[{"date":"2026-02-12","score":97,"grade":"A","inspection_type":"Routine","comments":"","violations":[{"code":"44:02:07:22","description":"Preventing contamination during storage. — --Food item was not stored in a clean, dry location a minimum of 6 inches above the floor. Boxes of food were stored on the floor in the back walk in freezer.","severity":"critical","corrected":false},{"code":"44:02:07:55","description":"Cleaning frequency of equipment and utensils. — --Nonfood contact surface was not cleaned as frequently as required. Gaskets on the reach in cooler and freezer in the kitchen need to be cleaned.","severity":"major","corrected":false}],"violation_count":2},{"date":"2025-04-07","score":97,"grade":"A","inspection_type":"Routine","comments":"","violation_count":2,"violations":[{"code":"32","description":"Proper storage, no-reuse (1 pt deducted)","severity":"minor","corrected":false},{"code":"7","description":"Clean/dry location, protected, covered, original containers, labeled (2 pts deducted)","severity":"minor","corrected":false}]},{"date":"2024-11-18","score":100,"grade":"A","inspection_type":"Routine","comments":"","violation_count":0,"violations":[]}],"score_history":[{"date":"2024-11-18","score":100},{"date":"2025-04-07","score":97},{"date":"2026-02-12","score":97}],"score_trend":"flat","violation_history":[{"date":"2024-11-18","count":0},{"date":"2025-04-07","count":2},{"date":"2026-02-12","count":2}],"violation_trend":"flat"}
