{"id":"sd_doh_the-daily-grind-313-main-ave-lemmon","name":"THE DAILY GRIND","address":"313 MAIN AVE","city":"Lemmon","state":"SD","zip_code":null,"phone":null,"latitude":45.941765684971,"longitude":-102.159427584029,"source":"sd_doh","latest_score":99,"latest_inspection_date":"2026-03-16","average_score":98.8,"inspection_count":6,"has_critical_violations":true,"violation_categories":["contamination"],"inspections":[{"date":"2026-03-16","score":99,"grade":"A","inspection_type":"Routine","comments":"","violation_count":1,"violations":[{"code":"44:02:07:24","description":"Preventing contamination from equipment, utensils, and wiping cloths. — --In-use utensil was not properly stored during pauses in food preparation or dispensing. -Multiple scoops with handle in coffee powders.","severity":"critical","corrected":false}]},{"date":"2025-10-22","score":95,"grade":"A","inspection_type":"Routine","comments":"","violation_count":3,"violations":[{"code":"10","description":"Clean, proper use, storage, sanitizing solution (2 pts deducted)","severity":"minor","corrected":false},{"code":"26","description":"Thermometers provided, used, clean, and accurate (1 pt deducted)","severity":"minor","corrected":false},{"code":"27","description":"Properly designed, located, constructed, operated, maintained, cleaned and chemical test kit provided (2 pts deducted)","severity":"minor","corrected":false}]},{"date":"2025-05-29","score":100,"grade":"A","inspection_type":"Routine","comments":"","violations":[],"violation_count":0},{"date":"2025-01-30","score":99,"grade":"A","inspection_type":"Routine","comments":"","violation_count":1,"violations":[{"code":"32","description":"Proper storage, no-reuse (1 pt deducted)","severity":"minor","corrected":false}]},{"date":"2024-10-30","score":100,"grade":"A","inspection_type":"Follow-up","comments":"","violation_count":0,"violations":[]},{"date":"2024-08-08","score":100,"grade":"A","inspection_type":"Routine","comments":"","violation_count":0,"violations":[]}],"score_history":[{"date":"2024-08-08","score":100},{"date":"2024-10-30","score":100},{"date":"2025-01-30","score":99},{"date":"2025-05-29","score":100},{"date":"2025-10-22","score":95},{"date":"2026-03-16","score":99}],"score_trend":"up","violation_history":[{"date":"2024-08-08","count":0},{"date":"2024-10-30","count":0},{"date":"2025-01-30","count":1},{"date":"2025-05-29","count":0},{"date":"2025-10-22","count":3},{"date":"2026-03-16","count":1}],"violation_trend":"up"}
