{"id":"sd_doh_lavas-coffee-305-w-willow-st-harrisburg","name":"LAVAS COFFEE","address":"305 W WILLOW ST","city":"Harrisburg","state":"SD","zip_code":null,"phone":"605-261-1568","latitude":43.431104,"longitude":-96.7064119,"source":"sd_doh","latest_score":98,"latest_inspection_date":"2026-04-16","average_score":97.5,"inspection_count":4,"has_critical_violations":false,"violation_categories":["cleanliness"],"inspections":[{"date":"2026-04-16","score":98,"grade":"A","inspection_type":"Routine","comments":"","violation_count":2,"violations":[{"code":"44:02:07:55","description":"Cleaning frequency of equipment and utensils. — --Nonfood contact surface * was not cleaned as frequently as required. - Inside refrigerator needs to be cleaned.","severity":"major","corrected":false},{"code":"44:02:07:77","description":"Cleaning and maintenance of floors, walls and ceilings. — --Physical facilities (e.g. floors, walls, ceiling etc…)* were not clean or not cleaned as often as necessary to keep them clean. - Floors require a more thorough cleaning.","severity":"minor","corrected":false}]},{"date":"2025-09-16","score":100,"grade":"A","inspection_type":"Routine","comments":"","violations":[],"violation_count":0},{"date":"2025-02-12","score":97,"grade":"A","inspection_type":"Routine","comments":"","violation_count":1,"violations":[{"code":"37","description":"Number, location, accessibility, soap and paper towels provided (3 pts deducted)","severity":"critical","corrected":false}]},{"date":"2024-07-31","score":95,"grade":"A","inspection_type":"Routine","comments":"","violation_count":3,"violations":[{"code":"32","description":"Proper storage, no-reuse (1 pt deducted)","severity":"minor","corrected":false},{"code":"9","description":"Storage, properly handled (1 pt deducted)","severity":"minor","corrected":false},{"code":"22","description":"Cleaning frequency, maintained clean (2 pts deducted)","severity":"minor","corrected":false},{"code":"23","description":"Cleaning frequency, maintained clean (1 pt deducted)","severity":"minor","corrected":false}]}],"score_history":[{"date":"2024-07-31","score":95},{"date":"2025-02-12","score":97},{"date":"2025-09-16","score":100},{"date":"2026-04-16","score":98}],"score_trend":"down","violation_history":[{"date":"2024-07-31","count":4},{"date":"2025-02-12","count":1},{"date":"2025-09-16","count":0},{"date":"2026-04-16","count":2}],"violation_trend":"down","geo_precision":"address","source_address":"305 W WILLOW ST, Harrisburg"}
