{"id":"sd_doh_corner-pantry-33-1312-river-dr-north-sioux-city","name":"CORNER PANTRY 33","address":"1312 RIVER DR","city":"North Sioux City","state":"SD","zip_code":null,"phone":null,"latitude":42.524548296719,"longitude":-96.502379934626,"source":"sd_doh","latest_score":99,"latest_inspection_date":"2026-04-17","average_score":98,"inspection_count":4,"has_critical_violations":false,"violation_categories":["equipment"],"inspections":[{"date":"2026-04-17","score":99,"grade":"A","inspection_type":"Routine","comments":"","violation_count":1,"violations":[{"code":"44:02:07:61","description":"Single-service and single-use articles. — --Single-service item was not stored in a proper location to be protected from contamination. Plastic cups were found stored on the floor in the kitchen. Single use items should be stored off of the floor.","severity":"major","corrected":false}]},{"date":"2025-07-15","score":99,"grade":"A","inspection_type":"Routine","comments":"","violations":[{"code":"44:02:07:77","description":"Cleaning and maintenance of floors, walls and ceilings. — --Physical facilities (e.g. floors, walls, ceiling etc…) were not clean or not cleaned as often as necessary to keep them clean. Ceiling tiles above the hand washing sink in the kitchen were found dirty. These should be cleaned and maintained clean.","severity":"minor","corrected":false}],"violation_count":1},{"date":"2025-01-08","score":94,"grade":"A","inspection_type":"Routine","comments":"","violation_count":2,"violations":[{"code":"40","description":"Design, construction, clean, maintained (1 pt deducted)","severity":"minor","corrected":false},{"code":"14","description":"Cooking and reheating to the proper time and temperature (5 pts deducted)","severity":"critical","corrected":false}]},{"date":"2024-07-17","score":100,"grade":"A","inspection_type":"Routine","comments":"","violation_count":0,"violations":[]}],"score_history":[{"date":"2024-07-17","score":100},{"date":"2025-01-08","score":94},{"date":"2025-07-15","score":99},{"date":"2026-04-17","score":99}],"score_trend":"flat","violation_history":[{"date":"2024-07-17","count":0},{"date":"2025-01-08","count":2},{"date":"2025-07-15","count":1},{"date":"2026-04-17","count":1}],"violation_trend":"flat"}
