{"id":"sd_doh_candyland-23835-mill-iron-dr-rapid-city","name":"CANDYLAND","address":"23835 Mill Iron DR","city":"Rapid City","state":"SD","zip_code":null,"phone":null,"latitude":44.08004676751621,"longitude":-103.21984546889745,"source":"sd_doh","latest_score":99,"latest_inspection_date":"2026-05-13","average_score":99.5,"inspection_count":4,"has_critical_violations":false,"violation_categories":["equipment"],"inspections":[{"date":"2026-05-13","score":99,"grade":"A","inspection_type":"Routine","comments":"","violation_count":1,"violations":[{"code":"44:02:07:43","description":"General equipment and utensils - Materials and design. — --Material of nonfood contact surface was not constructed or designed to be smooth, nonabsorbent and cleanable. - New wooden racks for storage need to be sealed or painted.","severity":"major","corrected":false}]},{"date":"2025-09-29","score":100,"grade":"A","inspection_type":"Routine","comments":"","violations":[],"violation_count":0},{"date":"2025-03-21","score":99,"grade":"A","inspection_type":"Routine","comments":"","violation_count":1,"violations":[{"code":"21","description":"Designed, constructed, installed, and maintained (1 pt deducted)","severity":"minor","corrected":false}]},{"date":"2024-12-20","score":100,"grade":"A","inspection_type":"Routine","comments":"","violation_count":0,"violations":[]}],"score_history":[{"date":"2024-12-20","score":100},{"date":"2025-03-21","score":99},{"date":"2025-09-29","score":100},{"date":"2026-05-13","score":99}],"score_trend":"down","violation_history":[{"date":"2024-12-20","count":0},{"date":"2025-03-21","count":1},{"date":"2025-09-29","count":0},{"date":"2026-05-13","count":1}],"violation_trend":"down","geo_precision":"city","source_address":null}
