{"id":"sd_doh_beauty-brew-coffee-boutique-100-n-main-st-groton","name":"BEAUTY BREW COFFEE & BOUTIQUE","address":"100 N MAIN ST","city":"Groton","state":"SD","zip_code":null,"phone":null,"latitude":45.446314592275,"longitude":-98.098790004194,"source":"sd_doh","latest_score":100,"latest_inspection_date":"2026-02-25","average_score":100,"inspection_count":4,"has_critical_violations":false,"violation_categories":[],"score_history":[{"date":"2024-07-25","score":100},{"date":"2025-01-15","score":100},{"date":"2025-07-21","score":100},{"date":"2026-02-25","score":100}],"score_trend":"flat","violation_history":[{"date":"2024-07-25","count":0},{"date":"2025-01-15","count":0},{"date":"2025-07-21","count":0},{"date":"2026-02-25","count":0}],"violation_trend":"flat","inspections":[{"date":"2026-02-25","score":100,"grade":"A","inspection_type":"Routine","comments":"","violation_count":0,"violations":[]},{"date":"2025-07-21","score":100,"grade":"A","inspection_type":"Routine","comments":"","violation_count":0,"violations":[]},{"date":"2025-01-15","score":100,"grade":"A","inspection_type":"Routine","comments":"","violation_count":0,"violations":[]},{"date":"2024-07-25","score":100,"grade":"A","inspection_type":"Routine","comments":"","violation_count":0,"violations":[]}]}
