{"id":"sd_doh_the-fix-1-22661-merchen-rd-rapid-city","name":"THE FIX - 1","address":"22661 Merchen RD","city":"Rapid City","state":"SD","zip_code":null,"phone":null,"latitude":44.115898789677,"longitude":-103.41279519577,"source":"sd_doh","latest_score":97,"latest_inspection_date":"2026-02-02","average_score":97,"inspection_count":1,"has_critical_violations":false,"violation_categories":["handwashing"],"inspections":[{"date":"2026-02-02","score":97,"grade":"A","inspection_type":"Routine","comments":"","violations":[{"code":"44:02:07:68","description":"Handwashing lavatories. — --Handwashing lavatory was used for purpose other than handwashing. -Milk and juice cartons stored in handwash sink.","severity":"minor","corrected":false}]}],"score_history":[{"date":"2026-02-02","score":97}],"score_trend":null,"violation_history":[{"date":"2026-02-02","count":1}],"violation_trend":null}
