{"id":"sd_doh_southern-hills-golf-course-1130-clubhouse-dr-hot-springs","name":"SOUTHERN HILLS GOLF COURSE","address":"1130 Clubhouse DR","city":"Hot Springs","state":"SD","zip_code":null,"phone":"605-745-6400","latitude":43.424134,"longitude":-103.5021041,"source":"sd_doh","latest_score":100,"latest_inspection_date":"2026-06-15","average_score":99.8,"inspection_count":4,"has_critical_violations":false,"violation_categories":[],"score_history":[{"date":"2024-09-10","score":100},{"date":"2025-05-12","score":99},{"date":"2025-08-25","score":100},{"date":"2026-06-15","score":100}],"score_trend":"flat","violation_history":[{"date":"2024-09-10","count":0},{"date":"2025-05-12","count":1},{"date":"2025-08-25","count":0},{"date":"2026-06-15","count":0}],"violation_trend":"flat","geo_precision":"address","source_address":"1130 Clubhouse DR, Hot Springs","inspections":[{"date":"2026-06-15","score":100,"grade":"A","inspection_type":"Routine","comments":"","violation_count":0,"violations":[]},{"date":"2025-08-25","score":100,"grade":"A","inspection_type":"Routine","comments":"","violation_count":0,"violations":[]},{"date":"2025-05-12","score":99,"grade":"A","inspection_type":"Routine","comments":"","violation_count":1,"violations":[]},{"date":"2024-09-10","score":100,"grade":"A","inspection_type":"Routine","comments":"","violation_count":0,"violations":[]}]}
