{"id":"sd_doh_jimmy-johns-2025-dakota-ave-huron","name":"JIMMY JOHNS","address":"2025 DAKOTA AVE","city":"Huron","state":"SD","zip_code":null,"phone":null,"latitude":44.3426771,"longitude":-98.214281,"source":"sd_doh","latest_score":100,"latest_inspection_date":"2026-07-02","average_score":98.5,"inspection_count":4,"has_critical_violations":false,"violation_categories":[],"inspections":[{"date":"2026-07-02","score":100,"grade":"A","inspection_type":"Routine","comments":"","violation_count":0,"violations":[]},{"date":"2026-01-08","score":97,"grade":"A","inspection_type":"Routine","comments":"","violations":[{"code":"44:02:07:68","description":"Handwashing lavatories. — --Handwashing lavatory was used for purpose other than handwashing. -Observed dumped ice in hand sink upon arrival.","severity":"minor","corrected":false}],"violation_count":1},{"date":"2025-07-14","score":100,"grade":"A","inspection_type":"Routine","comments":"","violation_count":0,"violations":[]},{"date":"2025-01-09","score":97,"grade":"A","inspection_type":"Routine","comments":"","violation_count":1,"violations":[{"code":"37","description":"Number, location, accessibility, soap and paper towels provided (3 pts deducted)","severity":"critical","corrected":false}]}],"score_history":[{"date":"2025-01-09","score":97},{"date":"2025-07-14","score":100},{"date":"2026-01-08","score":97},{"date":"2026-07-02","score":100}],"score_trend":"up","violation_history":[{"date":"2025-01-09","count":1},{"date":"2025-07-14","count":0},{"date":"2026-01-08","count":1},{"date":"2026-07-02","count":0}],"violation_trend":"up"}
