{"id":"sd_doh_ruby-tuesday-1900-highlandway-mitchell","name":"RUBY TUESDAY","address":"1900 Highlandway","city":"Mitchell","state":"SD","zip_code":null,"phone":"605-996-5208","latitude":43.690738,"longitude":-98.009476,"source":"sd_doh","latest_score":100,"latest_inspection_date":"2026-06-15","average_score":99.5,"inspection_count":4,"has_critical_violations":false,"violation_categories":[],"inspections":[{"date":"2026-06-15","score":100,"grade":"A","inspection_type":"Routine","comments":"","violation_count":0,"violations":[]},{"date":"2025-11-17","score":99,"grade":"A","inspection_type":"Routine","comments":"","violations":[{"code":"44:02:07:77","description":"Cleaning and maintenance of floors, walls and ceilings. — --Physical facilities (e.g. floors, walls, ceiling etc…)were not maintained in good repair. -Observed cracked floor tile in walk in cooler.","severity":"minor","corrected":false}],"violation_count":1},{"date":"2025-05-19","score":99,"grade":"A","inspection_type":"Routine","comments":"","violation_count":1,"violations":[{"code":"40","description":"Design, construction, clean, maintained (1 pt deducted)","severity":"minor","corrected":false}]},{"date":"2024-11-04","score":100,"grade":"A","inspection_type":"Routine","comments":"","violation_count":0,"violations":[]}],"score_history":[{"date":"2024-11-04","score":100},{"date":"2025-05-19","score":99},{"date":"2025-11-17","score":99},{"date":"2026-06-15","score":100}],"score_trend":"up","violation_history":[{"date":"2024-11-04","count":0},{"date":"2025-05-19","count":1},{"date":"2025-11-17","count":1},{"date":"2026-06-15","count":0}],"violation_trend":"up","geo_precision":"address","source_address":"1900 Highlandway, Mitchell"}
