{"id":"sf_sweeps_130","name":"FRYN' PAN","address":"4204 W 41ST ST","city":"Sioux Falls","state":"SD","zip_code":null,"phone":null,"latitude":43.514896038298,"longitude":-96.776833684464,"source":"sf_sweeps","latest_score":97,"latest_inspection_date":"2026-03-04","average_score":97.5,"inspection_count":2,"has_critical_violations":false,"violation_categories":["cleanliness"],"inspections":[{"date":"2026-03-04","score":97,"grade":"A","inspection_type":"Routine","comments":"","violations":[{"code":"22","description":"FOOD CONTACT SURFACES - CLEAN (2 pts): Ice machine interior (mildew/rust staining on grey chute) and can opener noted not properly maintained.","severity":"minor","corrected":false},{"code":"23","description":"NON FOOD CONTACT SURFACES - CLEAN (1 pts): Fan guards in the walk-in cooler (with eggs breakfast items eg.) noted not clean","severity":"minor","corrected":false}],"violation_count":2},{"date":"2025-11-24","score":98,"grade":"A","inspection_type":"Routine","comments":"","violations":[{"code":"40","description":"FLOORS WALLS CEILINGS (1 pts): Floors in the walk-in freezers and under the ware-wash area noted in need of cleaning.","severity":"minor","corrected":false},{"code":"21","description":"NON FOOD CONTACT SURFACES - DESIGN (1 pts): Reachin cooler/freezer door gaskets noted not in good repair.","severity":"minor","corrected":false}],"violation_count":2}],"score_history":[{"date":"2025-11-24","score":98},{"date":"2026-03-04","score":97}],"score_trend":"down","violation_history":[{"date":"2025-11-24","count":2},{"date":"2026-03-04","count":2}],"violation_trend":"flat"}
