{"id":"sf_sweeps_4171","name":"CIRCLE K #2746493","address":"3000 E 26TH ST","city":"Sioux Falls","state":"SD","zip_code":null,"phone":null,"latitude":43.529855,"longitude":-96.6883559,"source":"sf_sweeps","latest_score":100,"latest_inspection_date":"2026-01-27","average_score":99.5,"inspection_count":2,"has_critical_violations":false,"violation_categories":[],"inspections":[{"date":"2026-01-27","score":100,"grade":"A","inspection_type":"Routine","comments":"","violations":[],"violation_count":0},{"date":"2025-08-05","score":99,"grade":"A","inspection_type":"Routine","comments":"","violations":[{"code":"31","description":"STORAGE/HANDLING CLEAN EQUIP & UTENSILS (1 pts): Clean Food equipment noted stored in an unprotected location. The top shelf of the storage shelf is unprotected and exposed to the unprotected ceiling area.","severity":"minor","corrected":false}],"violation_count":1}],"score_history":[{"date":"2025-08-05","score":99},{"date":"2026-01-27","score":100}],"score_trend":"up","violation_history":[{"date":"2025-08-05","count":1},{"date":"2026-01-27","count":0}],"violation_trend":"up","geo_precision":"rooftop","source_address":null}
